{
  "affaires": [
    {
      "id": 1,
      "location": "Paris"
    },
    {
      "id": 2,
      "location": "Marseille"
    },
    {
      "id": 3,
      "location": "Lyon"
    },
    {
      "affaireId": "psCase-kx0gtvii",
      "ijOwners": [],
      "users": [],
      "selections": [],
      "validSteps": [],
      "updatedAt": "2021-12-10T14:09:26.735Z",
      "status": "inProgress",
      "gotStoredAffaire": false,
      "_id": "psCase-kx0gtvii",
      "localUpdate": 1639145366735,
      "modifier": {},
      "id": 4
    },
    {
      "affaireId": "psCase-kx0gugrv",
      "ijOwners": [],
      "users": [],
      "selections": [],
      "validSteps": [],
      "updatedAt": "2021-12-10T14:09:54.296Z",
      "status": "inProgress",
      "gotStoredAffaire": false,
      "_id": "psCase-kx0gugrv",
      "localUpdate": 1639145394297,
      "modifier": {},
      "id": 5
    },
    {
      "affaireId": "psCase-kx0gugrv",
      "ijOwners": [],
      "users": [],
      "selections": [],
      "validSteps": [],
      "updatedAt": "2021-12-10T14:10:01.961Z",
      "status": "inProgress",
      "gotStoredAffaire": false,
      "_id": "psCase-kx0gugrv",
      "localUpdate": 1639145401961,
      "modifier": {},
      "id": 6
    },
    {
      "affaireId": "psCase-kx0gugrv",
      "ijOwners": [],
      "users": [],
      "selections": [],
      "validSteps": [],
      "updatedAt": "2021-12-10T14:10:10.095Z",
      "status": "inProgress",
      "gotStoredAffaire": false,
      "_id": "psCase-kx0gugrv",
      "localUpdate": 1639145410095,
      "modifier": {},
      "id": 7
    },
    {
      "affaireId": "psCase-kx0gugrv",
      "ijOwners": [],
      "users": [],
      "selections": [],
      "validSteps": [],
      "updatedAt": "2021-12-10T14:10:12.386Z",
      "status": "inProgress",
      "gotStoredAffaire": false,
      "_id": "psCase-kx0gugrv",
      "localUpdate": 1639145412386,
      "modifier": {},
      "id": 8
    },
    {
      "affaireId": "psCase-kx0gv28a",
      "ijOwners": [],
      "users": [],
      "selections": [],
      "validSteps": [],
      "updatedAt": "2021-12-10T14:10:22.093Z",
      "status": "inProgress",
      "gotStoredAffaire": false,
      "_id": "psCase-kx0gv28a",
      "localUpdate": 1639145422093,
      "modifier": {},
      "id": 9
    },
    {
      "affaireId": "psCase-kx0gwdec",
      "ijOwners": [],
      "users": [],
      "selections": [],
      "validSteps": [],
      "updatedAt": "2021-12-10T14:11:23.221Z",
      "status": "inProgress",
      "gotStoredAffaire": false,
      "_id": "psCase-kx0gwdec",
      "localUpdate": 1639145483222,
      "modifier": {},
      "id": 10
    },
    {
      "affaireId": "psCase-kx0gwdec",
      "ijOwners": [],
      "users": [],
      "selections": [],
      "validSteps": [],
      "updatedAt": "2021-12-10T14:11:27.323Z",
      "status": "inProgress",
      "gotStoredAffaire": false,
      "_id": "psCase-kx0gwdec",
      "localUpdate": 1639145487323,
      "modifier": {},
      "id": 11
    },
    {
      "affaireId": "psCase-kx0gwdec",
      "ijOwners": [],
      "users": [],
      "selections": [],
      "validSteps": [],
      "updatedAt": "2021-12-10T14:11:31.408Z",
      "status": "inProgress",
      "gotStoredAffaire": false,
      "_id": "psCase-kx0gwdec",
      "localUpdate": 1639145491408,
      "modifier": {},
      "id": 12
    },
    {
      "affaireId": "psCase-kx0gx1ex",
      "ijOwners": [],
      "users": [],
      "selections": [],
      "validSteps": [],
      "updatedAt": "2021-12-10T14:11:54.349Z",
      "status": "inProgress",
      "gotStoredAffaire": false,
      "_id": "psCase-kx0gx1ex",
      "localUpdate": 1639145514349,
      "modifier": {},
      "id": 13
    },
    {
      "affaireId": "psCase-kx0gxh8i",
      "ijOwners": [],
      "users": [],
      "selections": [],
      "validSteps": [],
      "updatedAt": "2021-12-10T14:12:14.857Z",
      "status": "inProgress",
      "gotStoredAffaire": false,
      "_id": "psCase-kx0gxh8i",
      "localUpdate": 1639145534858,
      "modifier": {},
      "id": 14
    },
    {
      "affaireId": "psCase-kx0gxv9r",
      "ijOwners": [],
      "users": [],
      "selections": [],
      "validSteps": [],
      "updatedAt": "2021-12-10T14:12:33.042Z",
      "status": "inProgress",
      "gotStoredAffaire": false,
      "_id": "psCase-kx0gxv9r",
      "localUpdate": 1639145553042,
      "modifier": {},
      "id": 15
    },
    {
      "affaireId": "psCase-kx0gzh85",
      "ijOwners": [],
      "users": [],
      "selections": [],
      "validSteps": [],
      "updatedAt": "2021-12-10T14:13:48.168Z",
      "status": "inProgress",
      "gotStoredAffaire": false,
      "_id": "psCase-kx0gzh85",
      "localUpdate": 1639145628169,
      "modifier": {},
      "id": 16
    },
    {
      "affaireId": "psCase-kx0h5gm6",
      "ijOwners": [],
      "users": [],
      "selections": [],
      "validSteps": [],
      "updatedAt": "2021-12-10T14:18:27.303Z",
      "status": "inProgress",
      "gotStoredAffaire": false,
      "_id": "psCase-kx0h5gm6",
      "localUpdate": 1639145907303,
      "modifier": {},
      "id": 17
    },
    {
      "affaireId": "psCase-kx0h8pdr",
      "ijOwners": [],
      "users": [],
      "selections": [],
      "validSteps": [],
      "updatedAt": "2021-12-10T14:20:58.635Z",
      "status": "inProgress",
      "gotStoredAffaire": false,
      "_id": "psCase-kx0h8pdr",
      "localUpdate": 1639146058636,
      "modifier": {},
      "id": 18
    },
    {
      "affaireId": "psCase-kx0hbnrf",
      "ijOwners": [],
      "users": [],
      "selections": [],
      "validSteps": [],
      "updatedAt": "2021-12-10T14:23:16.505Z",
      "status": "inProgress",
      "gotStoredAffaire": false,
      "_id": "psCase-kx0hbnrf",
      "localUpdate": 1639146196505,
      "modifier": {},
      "id": 19
    },
    {
      "affaireId": "psCase-kx0hdb0g",
      "ijOwners": [],
      "users": [],
      "selections": [],
      "validSteps": [],
      "updatedAt": "2021-12-10T14:24:33.282Z",
      "status": "inProgress",
      "gotStoredAffaire": false,
      "_id": "psCase-kx0hdb0g",
      "localUpdate": 1639146273282,
      "modifier": {},
      "id": 20
    }
  ]
}